emphub_cli/__init__.py
emphub_cli/cli.py
emphub_cli/commands.py
emphub_cli/func.py
emphub_cli/miniohelpers.py
emphub_cli/operations.py
emphub_cli-0.1.0.dist-info/METADATA
emphub_cli-0.1.0.dist-info/WHEEL
emphub_cli-0.1.0.dist-info/entry_points.txt
emphub_cli-0.1.0.dist-info/licenses/LICENSE
emphub_cli-0.1.0.dist-info/RECORD
