Metadata-Version: 2.4
Name: emphub-cli
Version: 0.1.0
Summary: CLI tools to interface with EMPHub
Project-URL: Homepage, https://gitlab.cern.ch/dmonk/emphub-cli
Project-URL: Issues, https://gitlab.cern.ch/dmonk/emphub-cli/issues
Author-email: David Monk <dmonk@cern.ch>
License-Expression: MIT
License-File: LICENSE
Classifier: Operating System :: OS Independent
Classifier: Programming Language :: Python :: 3
Requires-Python: >=3.6
Requires-Dist: click
Requires-Dist: minio
Requires-Dist: pyyaml
Requires-Dist: tabulate
